{
  "input": {
    "molecule": {
      "cavity_coords": [
        {
          "center": [
            0.0,
            0.0,
            -2.0437794884379255
          ],
          "radius": 0.65
        },
        {
          "center": [
            0.0,
            0.0,
            0.9223344215620743
          ],
          "radius": 0.97
        }
      ],
      "cavity_width": 0.2,
      "charge": 0,
      "coords": [
        {
          "atom": "o",
          "xyz": [
            0.0,
            0.0,
            -2.0437794884379255
          ]
        },
        {
          "atom": "cl",
          "xyz": [
            0.0,
            0.0,
            0.9223344215620743
          ]
        }
      ],
      "multiplicity": 2
    },
    "mpi": {
      "bank_size": 1,
      "numerically_exact": false,
      "shared_memory_size": 10000
    },
    "mra": {
      "basis_order": 9,
      "basis_type": "interpolating",
      "boxes": [
        2,
        2,
        2
      ],
      "corner": [
        -1,
        -1,
        -1
      ],
      "max_scale": 20,
      "min_scale": -5
    },
    "printer": {
      "file_name": "cl_6_pbe0_.inp",
      "print_level": 0,
      "print_mpi": false,
      "print_prec": 6,
      "print_width": 75
    },
    "rsp_calculations": {},
    "scf_calculation": {
      "fock_operator": {
        "coulomb_operator": {
          "poisson_prec": 1e-06,
          "shared_memory": true
        },
        "exchange_operator": {
          "exchange_prec": -1.0,
          "poisson_prec": 1e-06
        },
        "kinetic_operator": {
          "derivative": "abgv_55"
        },
        "nuclear_operator": {
          "proj_prec": 1e-06,
          "shared_memory": true,
          "smooth_prec": 1e-06
        },
        "xc_operator": {
          "shared_memory": false,
          "xc_functional": {
            "cutoff": 0.0,
            "functionals": [
              {
                "coef": 1.0,
                "name": "pbe0"
              }
            ],
            "spin": true
          }
        }
      },
      "initial_guess": {
        "file_CUBE_a": "cube_vectors/CUBE_a_vector.json",
        "file_CUBE_b": "cube_vectors/CUBE_b_vector.json",
        "file_CUBE_p": "cube_vectors/CUBE_p_vector.json",
        "file_basis": "initial_guess/mrchem.bas",
        "file_chk": "checkpoint/phi_scf",
        "file_gto_a": "initial_guess/mrchem.moa",
        "file_gto_b": "initial_guess/mrchem.mob",
        "file_gto_p": "initial_guess/mrchem.mop",
        "file_phi_a": "initial_guess/phi_a_scf",
        "file_phi_b": "initial_guess/phi_b_scf",
        "file_phi_p": "initial_guess/phi_p_scf",
        "localize": true,
        "method": "DFT (PBE0)",
        "prec": 0.0001,
        "relativity": "None",
        "restricted": false,
        "screen": 12.0,
        "type": "sad_gto",
        "zeta": 0
      },
      "properties": {
        "dipole_moment": {
          "dip-1": {
            "operator": "h_e_dip",
            "precision": 1e-06,
            "r_O": [
              0.0,
              0.0,
              0.0
            ]
          }
        }
      },
      "scf_solver": {
        "checkpoint": false,
        "derivative": "abgv_55",
        "energy_thrs": 1e-06,
        "file_chk": "checkpoint/phi_scf",
        "final_prec": 1e-06,
        "helmholtz_prec": -1.0,
        "kain": 10,
        "light_speed": -1.0,
        "localize": true,
        "max_iter": 200,
        "method": "DFT (PBE0)",
        "orbital_thrs": 4.9999999999999996e-05,
        "proj_prec": 1e-06,
        "relativity": "None",
        "rotation": 0,
        "shared_memory": true,
        "smooth_prec": 1e-06,
        "start_prec": 1e-06
      },
      "write_orbitals": {
        "file_phi_a": "orbitals/phi_a_scf",
        "file_phi_b": "orbitals/phi_b_scf",
        "file_phi_p": "orbitals/phi_p_scf"
      }
    },
    "schema_name": "mrchem_input",
    "schema_version": 1
  },
  "output": {
    "properties": {
      "center_of_mass": [
        0.0,
        0.0,
        1.8066232270833874e-16
      ],
      "charge": 0,
      "dipole_moment": {
        "dip-1": {
          "magnitude": 0.48958350617511837,
          "r_O": [
            0.0,
            0.0,
            0.0
          ],
          "vector": [
            -1.4412348588347594e-07,
            -5.77452743697785e-06,
            0.4895835061410425
          ],
          "vector_el": [
            -1.4426278439547136e-07,
            -5.774666831270814e-06,
            1.1601342470935725
          ],
          "vector_nuc": [
            1.3929851199541193e-10,
            1.3939429296358628e-10,
            -0.67055074095253
          ]
        }
      },
      "geometry": [
        {
          "symbol": "O",
          "xyz": [
            0.0,
            0.0,
            -2.0437794884379255
          ]
        },
        {
          "symbol": "Cl",
          "xyz": [
            0.0,
            0.0,
            0.9223344215620743
          ]
        }
      ],
      "multiplicity": 2,
      "orbital_energies": {
        "energy": [
          -101.79915790846991,
          -19.31031403524324,
          -9.619178609942713,
          -7.354082455969561,
          -7.350397910561923,
          -7.342156821612927,
          -1.1346156826206923,
          -0.8196559505422873,
          -0.511613358414306,
          -0.5090254789993632,
          -0.46916425419868185,
          -0.34736333226639743,
          -0.3069912956427473,
          -101.79685175203353,
          -19.289235070502937,
          -9.617066188694285,
          -7.353450496300646,
          -7.342047101793996,
          -7.340955783310311,
          -1.0966054312357103,
          -0.7843564642394948,
          -0.49250808898582743,
          -0.45946475642377743,
          -0.4271529012959261,
          -0.29314611481039154
        ],
        "occupation": [
          1.0,
          1.0,
          1.0,
          1.0,
          1.0,
          1.0,
          1.0,
          1.0,
          1.0,
          1.0,
          1.0,
          1.0,
          1.0,
          1.0,
          1.0,
          1.0,
          1.0,
          1.0,
          1.0,
          1.0,
          1.0,
          1.0,
          1.0,
          1.0,
          1.0
        ],
        "spin": [
          "a",
          "a",
          "a",
          "a",
          "a",
          "a",
          "a",
          "a",
          "a",
          "a",
          "a",
          "a",
          "a",
          "b",
          "b",
          "b",
          "b",
          "b",
          "b",
          "b",
          "b",
          "b",
          "b",
          "b",
          "b"
        ],
        "sum_occupied": -313.1665572441116
      },
      "scf_energy": {
        "E_ee": 284.79741602117963,
        "E_eext": 0.0,
        "E_el": -580.9943866523786,
        "E_en": -1363.591294091726,
        "E_kin": 534.320686031794,
        "E_next": 0.0,
        "E_nn": 45.85123974554302,
        "E_nuc": 45.85123974554302,
        "E_tot": -535.1431469068356,
        "E_x": -8.917991875204883,
        "E_xc": -27.603202738421324,
        "Er_el": 0.0,
        "Er_nuc": 0.0,
        "Er_tot": 0.0
      }
    },
    "provenance": {
      "creator": "MRChem",
      "mpi_processes": 30,
      "nthreads": 6,
      "routine": "mrchem.x",
      "total_cores": 180,
      "version": "1.1.0-alpha"
    },
    "rsp_calculations": null,
    "scf_calculation": {
      "initial_energy": {
        "E_ee": 284.145793063084,
        "E_eext": 0.0,
        "E_el": -578.2289385609823,
        "E_en": -1356.614233284519,
        "E_kin": 530.7488076975611,
        "E_next": 0.0,
        "E_nn": 45.85123974554302,
        "E_nuc": 45.85123974554302,
        "E_tot": -532.3776988154393,
        "E_x": -8.921777313956692,
        "E_xc": -27.587528723151614,
        "Er_el": 0.0,
        "Er_nuc": 0.0,
        "Er_tot": 0.0
      },
      "scf_solver": {
        "converged": true,
        "cycles": [
          {
            "energy_terms": {
              "E_ee": 283.72363969887476,
              "E_eext": 0.0,
              "E_el": -580.8786824958886,
              "E_en": -1357.4039108247573,
              "E_kin": 529.1804571980856,
              "E_next": 0.0,
              "E_nn": 45.85123974554302,
              "E_nuc": 45.85123974554302,
              "E_tot": -535.0274427503456,
              "E_x": -8.885613504943414,
              "E_xc": -27.493255063148254,
              "Er_el": 0.0,
              "Er_nuc": 0.0,
              "Er_tot": 0.0
            },
            "energy_total": -535.0274427503456,
            "energy_update": 2.649743934906269,
            "mo_residual": 0.2760399413031529,
            "wall_time": 193.494252772
          },
          {
            "energy_terms": {
              "E_ee": 284.6653702553422,
              "E_eext": 0.0,
              "E_el": -580.9684423547865,
              "E_en": -1361.3833060934558,
              "E_kin": 532.2452101721259,
              "E_next": 0.0,
              "E_nn": 45.85123974554302,
              "E_nuc": 45.85123974554302,
              "E_tot": -535.1172026092435,
              "E_x": -8.912658528159103,
              "E_xc": -27.58305816063975,
              "Er_el": 0.0,
              "Er_nuc": 0.0,
              "Er_tot": 0.0
            },
            "energy_total": -535.1172026092435,
            "energy_update": 0.08975985889787808,
            "mo_residual": 0.11281135174079421,
            "wall_time": 85.281369633
          },
          {
            "energy_terms": {
              "E_ee": 284.5127235375578,
              "E_eext": 0.0,
              "E_el": -580.9839284293298,
              "E_en": -1362.2903730242926,
              "E_kin": 533.2784619699319,
              "E_next": 0.0,
              "E_nn": 45.85123974554302,
              "E_nuc": 45.85123974554302,
              "E_tot": -535.1326886837868,
              "E_x": -8.9087176722586,
              "E_xc": -27.576023240268224,
              "Er_el": 0.0,
              "Er_nuc": 0.0,
              "Er_tot": 0.0
            },
            "energy_total": -535.1326886837868,
            "energy_update": 0.015486074543332506,
            "mo_residual": 0.06871936391294,
            "wall_time": 71.71595391
          },
          {
            "energy_terms": {
              "E_ee": 284.704366941294,
              "E_eext": 0.0,
              "E_el": -580.9884226259717,
              "E_en": -1362.9350458149986,
              "E_kin": 533.750555745102,
              "E_next": 0.0,
              "E_nn": 45.85123974554302,
              "E_nuc": 45.85123974554302,
              "E_tot": -535.1371828804287,
              "E_x": -8.914382828765358,
              "E_xc": -27.593916668603683,
              "Er_el": 0.0,
              "Er_nuc": 0.0,
              "Er_tot": 0.0
            },
            "energy_total": -535.1371828804287,
            "energy_update": 0.004494196641871895,
            "mo_residual": 0.03554504654227727,
            "wall_time": 73.276002116
          },
          {
            "energy_terms": {
              "E_ee": 284.84115718750013,
              "E_eext": 0.0,
              "E_el": -580.9926842152112,
              "E_en": -1363.9462248213767,
              "E_kin": 534.6396673488836,
              "E_next": 0.0,
              "E_nn": 45.85123974554302,
              "E_nuc": 45.85123974554302,
              "E_tot": -535.1414444696682,
              "E_x": -8.91837123268323,
              "E_xc": -27.608912697534848,
              "Er_el": 0.0,
              "Er_nuc": 0.0,
              "Er_tot": 0.0
            },
            "energy_total": -535.1414444696682,
            "energy_update": 0.004261589239490604,
            "mo_residual": 0.043364897832967625,
            "wall_time": 75.223516277
          },
          {
            "energy_terms": {
              "E_ee": 284.8232217433624,
              "E_eext": 0.0,
              "E_el": -580.993327769565,
              "E_en": -1363.9050035964683,
              "E_kin": 534.6129669060941,
              "E_next": 0.0,
              "E_nn": 45.85123974554302,
              "E_nuc": 45.85123974554302,
              "E_tot": -535.142088024022,
              "E_x": -8.917716060419478,
              "E_xc": -27.606796762133758,
              "Er_el": 0.0,
              "Er_nuc": 0.0,
              "Er_tot": 0.0
            },
            "energy_total": -535.142088024022,
            "energy_update": 0.0006435543538145794,
            "mo_residual": 0.014626195047221664,
            "wall_time": 74.229621858
          },
          {
            "energy_terms": {
              "E_ee": 284.79723948610996,
              "E_eext": 0.0,
              "E_el": -580.9939526968784,
              "E_en": -1363.5952468734051,
              "E_kin": 534.3231413166511,
              "E_next": 0.0,
              "E_nn": 45.85123974554302,
              "E_nuc": 45.85123974554302,
              "E_tot": -535.1427129513354,
              "E_x": -8.916731148320856,
              "E_xc": -27.60235547791339,
              "Er_el": 0.0,
              "Er_nuc": 0.0,
              "Er_tot": 0.0
            },
            "energy_total": -535.1427129513354,
            "energy_update": 0.0006249273134244504,
            "mo_residual": 0.017788521264040878,
            "wall_time": 79.351784644
          },
          {
            "energy_terms": {
              "E_ee": 284.7923920792205,
              "E_eext": 0.0,
              "E_el": -580.994077320425,
              "E_en": -1363.5152488106064,
              "E_kin": 534.2469040289099,
              "E_next": 0.0,
              "E_nn": 45.85123974554302,
              "E_nuc": 45.85123974554302,
              "E_tot": -535.142837574882,
              "E_x": -8.916664927390569,
              "E_xc": -27.60145969055851,
              "Er_el": 0.0,
              "Er_nuc": 0.0,
              "Er_tot": 0.0
            },
            "energy_total": -535.142837574882,
            "energy_update": 0.00012462354663966835,
            "mo_residual": 0.009013299455061234,
            "wall_time": 78.462699536
          },
          {
            "energy_terms": {
              "E_ee": 284.7766959259001,
              "E_eext": 0.0,
              "E_el": -580.9941987674008,
              "E_en": -1363.4971699969965,
              "E_kin": 534.2436343973601,
              "E_next": 0.0,
              "E_nn": 45.85123974554302,
              "E_nuc": 45.85123974554302,
              "E_tot": -535.1429590218578,
              "E_x": -8.916684078718363,
              "E_xc": -27.60067501494609,
              "Er_el": 0.0,
              "Er_nuc": 0.0,
              "Er_tot": 0.0
            },
            "energy_total": -535.1429590218578,
            "energy_update": 0.0001214469757542247,
            "mo_residual": 0.013379814703263052,
            "wall_time": 77.984608998
          },
          {
            "energy_terms": {
              "E_ee": 284.77169720928663,
              "E_eext": 0.0,
              "E_el": -580.9942704398957,
              "E_en": -1363.5334374367576,
              "E_kin": 534.2854907008893,
              "E_next": 0.0,
              "E_nn": 45.85123974554302,
              "E_nuc": 45.85123974554302,
              "E_tot": -535.1430306943527,
              "E_x": -8.91694097426513,
              "E_xc": -27.60107993904893,
              "Er_el": 0.0,
              "Er_nuc": 0.0,
              "Er_tot": 0.0
            },
            "energy_total": -535.1430306943527,
            "energy_update": 7.16724948688352e-05,
            "mo_residual": 0.00819417090918935,
            "wall_time": 78.908674404
          },
          {
            "energy_terms": {
              "E_ee": 284.78392177007106,
              "E_eext": 0.0,
              "E_el": -580.9943447868252,
              "E_en": -1363.607312725917,
              "E_kin": 534.3497185208317,
              "E_next": 0.0,
              "E_nn": 45.85123974554302,
              "E_nuc": 45.85123974554302,
              "E_tot": -535.1431050412822,
              "E_x": -8.917706341153412,
              "E_xc": -27.602966010657603,
              "Er_el": 0.0,
              "Er_nuc": 0.0,
              "Er_tot": 0.0
            },
            "energy_total": -535.1431050412822,
            "energy_update": 7.434692952301702e-05,
            "mo_residual": 0.010949353282208545,
            "wall_time": 76.196333804
          },
          {
            "energy_terms": {
              "E_ee": 284.79233980406326,
              "E_eext": 0.0,
              "E_el": -580.9943622551366,
              "E_en": -1363.6122265079778,
              "E_kin": 534.3468626024428,
              "E_next": 0.0,
              "E_nn": 45.85123974554302,
              "E_nuc": 45.85123974554302,
              "E_tot": -535.1431225095936,
              "E_x": -8.917902589344415,
              "E_xc": -27.603435564320435,
              "Er_el": 0.0,
              "Er_nuc": 0.0,
              "Er_tot": 0.0
            },
            "energy_total": -535.1431225095936,
            "energy_update": 1.7468311398260994e-05,
            "mo_residual": 0.0038282435287979,
            "wall_time": 79.788283741
          },
          {
            "energy_terms": {
              "E_ee": 284.79428736996755,
              "E_eext": 0.0,
              "E_el": -580.9943722074009,
              "E_en": -1363.5953438014199,
              "E_kin": 534.3278292234129,
              "E_next": 0.0,
              "E_nn": 45.85123974554302,
              "E_nuc": 45.85123974554302,
              "E_tot": -535.1431324618579,
              "E_x": -8.917876051174071,
              "E_xc": -27.603268948187477,
              "Er_el": 0.0,
              "Er_nuc": 0.0,
              "Er_tot": 0.0
            },
            "energy_total": -535.1431324618579,
            "energy_update": 9.952264349522011e-06,
            "mo_residual": 0.0024118620549393624,
            "wall_time": 76.580163105
          },
          {
            "energy_terms": {
              "E_ee": 284.79428591318015,
              "E_eext": 0.0,
              "E_el": -580.9943814602152,
              "E_en": -1363.5690656339302,
              "E_kin": 534.301019983923,
              "E_next": 0.0,
              "E_nn": 45.85123974554302,
              "E_nuc": 45.85123974554302,
              "E_tot": -535.1431417146722,
              "E_x": -8.917786609465,
              "E_xc": -27.602835113923057,
              "Er_el": 0.0,
              "Er_nuc": 0.0,
              "Er_tot": 0.0
            },
            "energy_total": -535.1431417146722,
            "energy_update": 9.252814265892084e-06,
            "mo_residual": 0.003059217750129028,
            "wall_time": 76.397607129
          },
          {
            "energy_terms": {
              "E_ee": 284.7953427183962,
              "E_eext": 0.0,
              "E_el": -580.9943841537956,
              "E_en": -1363.570054383268,
              "E_kin": 534.3010099778155,
              "E_next": 0.0,
              "E_nn": 45.85123974554302,
              "E_nuc": 45.85123974554302,
              "E_tot": -535.1431444082526,
              "E_x": -8.917829347220675,
              "E_xc": -27.60285311951874,
              "Er_el": 0.0,
              "Er_nuc": 0.0,
              "Er_tot": 0.0
            },
            "energy_total": -535.1431444082526,
            "energy_update": 2.693580427148845e-06,
            "mo_residual": 0.0016875090045535648,
            "wall_time": 73.765078625
          },
          {
            "energy_terms": {
              "E_ee": 284.7954036740773,
              "E_eext": 0.0,
              "E_el": -580.9943853523404,
              "E_en": -1363.583221298945,
              "E_kin": 534.3143174901974,
              "E_next": 0.0,
              "E_nn": 45.85123974554302,
              "E_nuc": 45.85123974554302,
              "E_tot": -535.1431456067974,
              "E_x": -8.91789218498967,
              "E_xc": -27.602993032680295,
              "Er_el": 0.0,
              "Er_nuc": 0.0,
              "Er_tot": 0.0
            },
            "energy_total": -535.1431456067974,
            "energy_update": 1.198544737235352e-06,
            "mo_residual": 0.0008515066325106588,
            "wall_time": 77.120925072
          },
          {
            "energy_terms": {
              "E_ee": 284.79644811226933,
              "E_eext": 0.0,
              "E_el": -580.9943858285066,
              "E_en": -1363.59136237125,
              "E_kin": 534.3216047775821,
              "E_next": 0.0,
              "E_nn": 45.85123974554302,
              "E_nuc": 45.85123974554302,
              "E_tot": -535.1431460829635,
              "E_x": -8.917941455849462,
              "E_xc": -27.603134891258662,
              "Er_el": 0.0,
              "Er_nuc": 0.0,
              "Er_tot": 0.0
            },
            "energy_total": -535.1431460829635,
            "energy_update": 4.76166178486892e-07,
            "mo_residual": 0.000452858864078664,
            "wall_time": 76.639238891
          },
          {
            "energy_terms": {
              "E_ee": 284.7975732865086,
              "E_eext": 0.0,
              "E_el": -580.9943861558221,
              "E_en": -1363.5942580549658,
              "E_kin": 534.323492680026,
              "E_next": 0.0,
              "E_nn": 45.85123974554302,
              "E_nuc": 45.85123974554302,
              "E_tot": -535.1431464102791,
              "E_x": -8.917972625438175,
              "E_xc": -27.60322144195268,
              "Er_el": 0.0,
              "Er_nuc": 0.0,
              "Er_tot": 0.0
            },
            "energy_total": -535.1431464102791,
            "energy_update": 3.2731554711062927e-07,
            "mo_residual": 0.00040143160048995415,
            "wall_time": 73.62047977
          },
          {
            "energy_terms": {
              "E_ee": 284.79795972584867,
              "E_eext": 0.0,
              "E_el": -580.9943863207164,
              "E_en": -1363.594537485184,
              "E_kin": 534.3234162998716,
              "E_next": 0.0,
              "E_nn": 45.85123974554302,
              "E_nuc": 45.85123974554302,
              "E_tot": -535.1431465751734,
              "E_x": -8.917981176798982,
              "E_xc": -27.603243684453822,
              "Er_el": 0.0,
              "Er_nuc": 0.0,
              "Er_tot": 0.0
            },
            "energy_total": -535.1431465751734,
            "energy_update": 1.6489434528921265e-07,
            "mo_residual": 0.0003565510398665572,
            "wall_time": 73.721322738
          },
          {
            "energy_terms": {
              "E_ee": 284.7979311976017,
              "E_eext": 0.0,
              "E_el": -580.9943864410452,
              "E_en": -1363.5922988427494,
              "E_kin": 534.3211796155955,
              "E_next": 0.0,
              "E_nn": 45.85123974554302,
              "E_nuc": 45.85123974554302,
              "E_tot": -535.1431466955022,
              "E_x": -8.917979060120489,
              "E_xc": -27.603219351372605,
              "Er_el": 0.0,
              "Er_nuc": 0.0,
              "Er_tot": 0.0
            },
            "energy_total": -535.1431466955022,
            "energy_update": 1.20328763841826e-07,
            "mo_residual": 0.00038134335655424557,
            "wall_time": 74.183284372
          },
          {
            "energy_terms": {
              "E_ee": 284.7976620180339,
              "E_eext": 0.0,
              "E_el": -580.9943865529422,
              "E_en": -1363.5903043196424,
              "E_kin": 534.319425484084,
              "E_next": 0.0,
              "E_nn": 45.85123974554302,
              "E_nuc": 45.85123974554302,
              "E_tot": -535.1431468073991,
              "E_x": -8.917979038716672,
              "E_xc": -27.60319069670107,
              "Er_el": 0.0,
              "Er_nuc": 0.0,
              "Er_tot": 0.0
            },
            "energy_total": -535.1431468073991,
            "energy_update": 1.1189695214852691e-07,
            "mo_residual": 0.000400515134423343,
            "wall_time": 73.705953234
          },
          {
            "energy_terms": {
              "E_ee": 284.7973394118169,
              "E_eext": 0.0,
              "E_el": -580.9943866090908,
              "E_en": -1363.5897722666296,
              "E_kin": 534.3192009856617,
              "E_next": 0.0,
              "E_nn": 45.85123974554302,
              "E_nuc": 45.85123974554302,
              "E_tot": -535.1431468635478,
              "E_x": -8.917980250992215,
              "E_xc": -27.60317448894771,
              "Er_el": 0.0,
              "Er_nuc": 0.0,
              "Er_tot": 0.0
            },
            "energy_total": -535.1431468635478,
            "energy_update": 5.614867859549122e-08,
            "mo_residual": 0.000254915380789788,
            "wall_time": 74.400616006
          },
          {
            "energy_terms": {
              "E_ee": 284.797301888494,
              "E_eext": 0.0,
              "E_el": -580.9943866337439,
              "E_en": -1363.5904549508948,
              "E_kin": 534.3199350100349,
              "E_next": 0.0,
              "E_nn": 45.85123974554302,
              "E_nuc": 45.85123974554302,
              "E_tot": -535.1431468882009,
              "E_x": -8.917985407505642,
              "E_xc": -27.603183173872466,
              "Er_el": 0.0,
              "Er_nuc": 0.0,
              "Er_tot": 0.0
            },
            "energy_total": -535.1431468882009,
            "energy_update": 2.4653104446770158e-08,
            "mo_residual": 0.00013483062479153088,
            "wall_time": 76.898616138
          },
          {
            "energy_terms": {
              "E_ee": 284.7973822709049,
              "E_eext": 0.0,
              "E_el": -580.9943866460479,
              "E_en": -1363.5911887247037,
              "E_kin": 534.320609608985,
              "E_next": 0.0,
              "E_nn": 45.85123974554302,
              "E_nuc": 45.85123974554302,
              "E_tot": -535.1431469005049,
              "E_x": -8.917991203128457,
              "E_xc": -27.603198598105735,
              "Er_el": 0.0,
              "Er_nuc": 0.0,
              "Er_tot": 0.0
            },
            "energy_total": -535.1431469005049,
            "energy_update": 1.2303985386097338e-08,
            "mo_residual": 0.0001028325566499005,
            "wall_time": 75.100901747
          },
          {
            "energy_terms": {
              "E_ee": 284.79741602117963,
              "E_eext": 0.0,
              "E_el": -580.9943866523786,
              "E_en": -1363.591294091726,
              "E_kin": 534.320686031794,
              "E_next": 0.0,
              "E_nn": 45.85123974554302,
              "E_nuc": 45.85123974554302,
              "E_tot": -535.1431469068356,
              "E_x": -8.917991875204883,
              "E_xc": -27.603202738421324,
              "Er_el": 0.0,
              "Er_nuc": 0.0,
              "Er_tot": 0.0
            },
            "energy_total": -535.1431469068356,
            "energy_update": 6.330651558528189e-09,
            "mo_residual": 6.936974381893142e-05,
            "wall_time": 92.146596932
          }
        ],
        "wall_time": 2038.25632202
      },
      "success": true
    },
    "schema_name": "mrchem_output",
    "schema_version": 1,
    "success": true
  }
}
