{
  "input": {
    "molecule": {
      "charge": 0,
      "coords": [
        {
          "atom": "s",
          "xyz": [
            0.0,
            0.0,
            0.10360312406116091
          ]
        },
        {
          "atom": "h",
          "xyz": [
            0.0,
            1.81716051,
            -1.6479838959388389
          ]
        },
        {
          "atom": "h",
          "xyz": [
            0.0,
            -1.81716051,
            -1.6479838959388389
          ]
        }
      ],
      "multiplicity": 1
    },
    "mpi": {
      "bank_size": 1,
      "numerically_exact": false,
      "shared_memory_size": 10000
    },
    "mra": {
      "basis_order": 9,
      "basis_type": "interpolating",
      "boxes": [
        2,
        2,
        2
      ],
      "corner": [
        -1,
        -1,
        -1
      ],
      "max_scale": 20,
      "min_scale": -5
    },
    "printer": {
      "file_name": "s_3_pbe_.inp",
      "print_level": 0,
      "print_mpi": false,
      "print_prec": 6,
      "print_width": 75
    },
    "rsp_calculations": {},
    "scf_calculation": {
      "fock_operator": {
        "coulomb_operator": {
          "poisson_prec": 1e-06,
          "shared_memory": true
        },
        "exchange_operator": {
          "exchange_prec": -1.0,
          "poisson_prec": 1e-06
        },
        "kinetic_operator": {
          "derivative": "abgv_55"
        },
        "nuclear_operator": {
          "proj_prec": 1e-06,
          "shared_memory": true,
          "smooth_prec": 1e-06
        },
        "xc_operator": {
          "shared_memory": false,
          "xc_functional": {
            "cutoff": 0.0,
            "functionals": [
              {
                "coef": 1.0,
                "name": "pbe"
              }
            ],
            "spin": true
          }
        }
      },
      "initial_guess": {
        "file_basis": "initial_guess/mrchem.bas",
        "file_chk": "checkpoint/phi_scf",
        "file_gto_a": "initial_guess/mrchem.moa",
        "file_gto_b": "initial_guess/mrchem.mob",
        "file_gto_p": "initial_guess/mrchem.mop",
        "file_phi_a": "initial_guess/phi_a_scf",
        "file_phi_b": "initial_guess/phi_b_scf",
        "file_phi_p": "initial_guess/phi_p_scf",
        "localize": true,
        "method": "DFT (PBE)",
        "prec": 0.0001,
        "restricted": false,
        "type": "sad",
        "zeta": 2
      },
      "properties": {
        "dipole_moment": {
          "dip-1": {
            "operator": "h_e_dip",
            "precision": 1e-06,
            "r_O": [
              0.0,
              0.0,
              0.0
            ]
          }
        }
      },
      "scf_solver": {
        "checkpoint": false,
        "energy_thrs": 1e-06,
        "file_chk": "checkpoint/phi_scf",
        "final_prec": 1e-06,
        "helmholtz_prec": -1.0,
        "kain": 10,
        "localize": true,
        "max_iter": 200,
        "method": "DFT (PBE)",
        "orbital_thrs": 4.9999999999999996e-05,
        "rotation": 0,
        "start_prec": 1e-06
      },
      "write_orbitals": {
        "file_phi_a": "orbitals/phi_a_scf",
        "file_phi_b": "orbitals/phi_b_scf",
        "file_phi_p": "orbitals/phi_p_scf"
      }
    },
    "schema_name": "mrchem_input",
    "schema_version": 1
  },
  "output": {
    "properties": {
      "center_of_mass": [
        0.0,
        -8.378291362178759e-20,
        -2.3007166518016302e-17
      ],
      "charge": 0,
      "dipole_moment": {
        "dip-1": {
          "magnitude": 0.38006658975280333,
          "r_O": [
            0.0,
            0.0,
            0.0
          ],
          "vector": [
            2.8602700533839465e-07,
            -5.760331432815924e-08,
            -0.38006658975269136
          ],
          "vector_el": [
            2.8592691904069656e-07,
            -5.7692542952648366e-08,
            1.2582512170694886
          ],
          "vector_nuc": [
            1.0008629769811918e-10,
            8.922862448912383e-11,
            -1.63831780682218
          ]
        }
      },
      "geometry": [
        {
          "symbol": "S",
          "xyz": [
            0.0,
            0.0,
            0.10360312406116091
          ]
        },
        {
          "symbol": "H",
          "xyz": [
            0.0,
            1.81716051,
            -1.6479838959388389
          ]
        },
        {
          "symbol": "H",
          "xyz": [
            0.0,
            -1.81716051,
            -1.6479838959388389
          ]
        }
      ],
      "multiplicity": 1,
      "orbital_energies": {
        "energy": [
          -88.04878044228235,
          -7.680298319830392,
          -5.701660249460816,
          -5.698324493530022,
          -5.691677173588732,
          -0.6809744579579149,
          -0.4063124915259549,
          -0.33359639391060786,
          -0.23161028722479043,
          -88.04878044229251,
          -7.680298319850825,
          -5.701660249526176,
          -5.698324493543043,
          -5.691677173581611,
          -0.6809744578890047,
          -0.40631249115201845,
          -0.33359639377192407,
          -0.23161028724513746
        ],
        "occupation": [
          1.0,
          1.0,
          1.0,
          1.0,
          1.0,
          1.0,
          1.0,
          1.0,
          1.0,
          1.0,
          1.0,
          1.0,
          1.0,
          1.0,
          1.0,
          1.0,
          1.0,
          1.0
        ],
        "spin": [
          "a",
          "a",
          "a",
          "a",
          "a",
          "a",
          "a",
          "a",
          "a",
          "b",
          "b",
          "b",
          "b",
          "b",
          "b",
          "b",
          "b",
          "b"
        ],
        "sum_occupied": -228.9464686181638
      },
      "scf_energy": {
        "E_ee": 190.91576936795406,
        "E_eext": 0.0,
        "E_el": -412.1969830021104,
        "E_en": -975.6046067334626,
        "E_kin": 398.7123128954124,
        "E_next": 0.0,
        "E_nn": 12.953887402931901,
        "E_nuc": 12.953887402931901,
        "E_tot": -399.2430955991785,
        "E_x": 0.0,
        "E_xc": -26.220458532014305
      }
    },
    "provenance": {
      "creator": "MRChem",
      "mpi_processes": 20,
      "nthreads": 6,
      "routine": "mrchem.x",
      "total_cores": 120,
      "version": "1.0.1"
    },
    "rsp_calculations": null,
    "scf_calculation": {
      "initial_energy": {
        "E_ee": 186.52105579207273,
        "E_eext": 0.0,
        "E_el": -410.7654667628494,
        "E_en": -982.9125921857658,
        "E_kin": 411.6974922233163,
        "E_next": 0.0,
        "E_nn": 12.953887402931901,
        "E_nuc": 12.953887402931901,
        "E_tot": -397.8115793599175,
        "E_x": 0.0,
        "E_xc": -26.071422592472715
      },
      "scf_solver": {
        "converged": true,
        "cycles": [
          {
            "energy_terms": {
              "E_ee": 192.00479994827145,
              "E_eext": 0.0,
              "E_el": -412.0712670239571,
              "E_en": -982.8243891426624,
              "E_kin": 405.1028023893306,
              "E_next": 0.0,
              "E_nn": 12.953887402931901,
              "E_nuc": 12.953887402931901,
              "E_tot": -399.1173796210252,
              "E_x": 0.0,
              "E_xc": -26.3544802188967
            },
            "energy_total": -399.1173796210252,
            "energy_update": 1.3058002611076631,
            "mo_residual": 0.7681639861200692,
            "wall_time": 68.198390053
          },
          {
            "energy_terms": {
              "E_ee": 191.16369331701483,
              "E_eext": 0.0,
              "E_el": -412.1794148750127,
              "E_en": -978.286049900611,
              "E_kin": 401.20782604308465,
              "E_next": 0.0,
              "E_nn": 12.953887402931901,
              "E_nuc": 12.953887402931901,
              "E_tot": -399.2255274720808,
              "E_x": 0.0,
              "E_xc": -26.264884334501097
            },
            "energy_total": -399.2255274720808,
            "energy_update": 0.10814785105560532,
            "mo_residual": 0.18198160695015128,
            "wall_time": 46.529001465
          },
          {
            "energy_terms": {
              "E_ee": 191.14452281012925,
              "E_eext": 0.0,
              "E_el": -412.1932696053079,
              "E_en": -976.9359214096203,
              "E_kin": 399.8482240445368,
              "E_next": 0.0,
              "E_nn": 12.953887402931901,
              "E_nuc": 12.953887402931901,
              "E_tot": -399.23938220237596,
              "E_x": 0.0,
              "E_xc": -26.25009505035363
            },
            "energy_total": -399.23938220237596,
            "energy_update": 0.013854730295179252,
            "mo_residual": 0.05441208421546254,
            "wall_time": 42.492524133
          },
          {
            "energy_terms": {
              "E_ee": 190.95229869734294,
              "E_eext": 0.0,
              "E_el": -412.1964110310415,
              "E_en": -975.9155359813063,
              "E_kin": 398.9939650968264,
              "E_next": 0.0,
              "E_nn": 12.953887402931901,
              "E_nuc": 12.953887402931901,
              "E_tot": -399.2425236281096,
              "E_x": 0.0,
              "E_xc": -26.22713884390455
            },
            "energy_total": -399.2425236281096,
            "energy_update": 0.0031414257336450646,
            "mo_residual": 0.0210865274366516,
            "wall_time": 42.185150179
          },
          {
            "energy_terms": {
              "E_ee": 190.92419752553997,
              "E_eext": 0.0,
              "E_el": -412.19690136609586,
              "E_en": -975.5817279053945,
              "E_kin": 398.6815605435204,
              "E_next": 0.0,
              "E_nn": 12.953887402931901,
              "E_nuc": 12.953887402931901,
              "E_tot": -399.24301396316395,
              "E_x": 0.0,
              "E_xc": -26.220931529761742
            },
            "energy_total": -399.24301396316395,
            "energy_update": 0.0004903350543372653,
            "mo_residual": 0.012027927751026839,
            "wall_time": 43.037542323
          },
          {
            "energy_terms": {
              "E_ee": 190.8986190026804,
              "E_eext": 0.0,
              "E_el": -412.1969575116911,
              "E_en": -975.5132794875403,
              "E_kin": 398.63593710656573,
              "E_next": 0.0,
              "E_nn": 12.953887402931901,
              "E_nuc": 12.953887402931901,
              "E_tot": -399.2430701087592,
              "E_x": 0.0,
              "E_xc": -26.21823413339691
            },
            "energy_total": -399.2430701087592,
            "energy_update": 5.614559523792195e-05,
            "mo_residual": 0.006834459545244462,
            "wall_time": 42.986934364
          },
          {
            "energy_terms": {
              "E_ee": 190.91324055219417,
              "E_eext": 0.0,
              "E_el": -412.1969805477996,
              "E_en": -975.5959251404902,
              "E_kin": 398.70583780516165,
              "E_next": 0.0,
              "E_nn": 12.953887402931901,
              "E_nuc": 12.953887402931901,
              "E_tot": -399.2430931448677,
              "E_x": 0.0,
              "E_xc": -26.220133764665245
            },
            "energy_total": -399.2430931448677,
            "energy_update": 2.3036108530050114e-05,
            "mo_residual": 0.002813500368278649,
            "wall_time": 43.160977276
          },
          {
            "energy_terms": {
              "E_ee": 190.91746007419917,
              "E_eext": 0.0,
              "E_el": -412.1969825988039,
              "E_en": -975.6145832862796,
              "E_kin": 398.7208101358031,
              "E_next": 0.0,
              "E_nn": 12.953887402931901,
              "E_nuc": 12.953887402931901,
              "E_tot": -399.243095195872,
              "E_x": 0.0,
              "E_xc": -26.220669522526546
            },
            "energy_total": -399.243095195872,
            "energy_update": 2.0510042872956546e-06,
            "mo_residual": 0.0009630806700203093,
            "wall_time": 44.132619373
          },
          {
            "energy_terms": {
              "E_ee": 190.9166339837599,
              "E_eext": 0.0,
              "E_el": -412.19698285689776,
              "E_en": -975.6067285754341,
              "E_kin": 398.71365231403524,
              "E_next": 0.0,
              "E_nn": 12.953887402931901,
              "E_nuc": 12.953887402931901,
              "E_tot": -399.24309545396585,
              "E_x": 0.0,
              "E_xc": -26.22054057925881
            },
            "energy_total": -399.24309545396585,
            "energy_update": 2.5809384851527284e-07,
            "mo_residual": 0.00040039296891505573,
            "wall_time": 44.333739781
          },
          {
            "energy_terms": {
              "E_ee": 190.91574012057717,
              "E_eext": 0.0,
              "E_el": -412.19698298705794,
              "E_en": -975.6034032693215,
              "E_kin": 398.7111224546999,
              "E_next": 0.0,
              "E_nn": 12.953887402931901,
              "E_nuc": 12.953887402931901,
              "E_tot": -399.243095584126,
              "E_x": 0.0,
              "E_xc": -26.22044229301357
            },
            "energy_total": -399.243095584126,
            "energy_update": 1.3016017419431591e-07,
            "mo_residual": 0.00019395900951569507,
            "wall_time": 45.263326715
          },
          {
            "energy_terms": {
              "E_ee": 190.91556160909184,
              "E_eext": 0.0,
              "E_el": -412.1969829952578,
              "E_en": -975.6036495403393,
              "E_kin": 398.711539478966,
              "E_next": 0.0,
              "E_nn": 12.953887402931901,
              "E_nuc": 12.953887402931901,
              "E_tot": -399.2430955923259,
              "E_x": 0.0,
              "E_xc": -26.220434542976243
            },
            "energy_total": -399.2430955923259,
            "energy_update": 8.199890544347e-09,
            "mo_residual": 0.00010003884001977979,
            "wall_time": 45.149995232
          },
          {
            "energy_terms": {
              "E_ee": 190.91576936795406,
              "E_eext": 0.0,
              "E_el": -412.1969830021104,
              "E_en": -975.6046067334626,
              "E_kin": 398.7123128954124,
              "E_next": 0.0,
              "E_nn": 12.953887402931901,
              "E_nuc": 12.953887402931901,
              "E_tot": -399.2430955991785,
              "E_x": 0.0,
              "E_xc": -26.220458532014305
            },
            "energy_total": -399.2430955991785,
            "energy_update": 6.852587830508128e-09,
            "mo_residual": 5.745957843026384e-05,
            "wall_time": 51.019186801
          }
        ],
        "wall_time": 558.528838418
      },
      "success": true
    },
    "schema_name": "mrchem_output",
    "schema_version": 1,
    "success": true
  }
}
