{
  "input": {
    "molecule": {
      "charge": 0,
      "coords": [
        {
          "atom": "c",
          "xyz": [
            1.0454708660425407,
            0.0,
            0.0
          ]
        },
        {
          "atom": "f",
          "xyz": [
            -0.44608985695745934,
            0.0,
            2.071517629
          ]
        },
        {
          "atom": "f",
          "xyz": [
            -0.44608985695745934,
            0.0,
            -2.071517629
          ]
        },
        {
          "atom": "h",
          "xyz": [
            2.1791174870425407,
            -1.706233595,
            0.0
          ]
        },
        {
          "atom": "h",
          "xyz": [
            2.1791174870425407,
            1.706233595,
            0.0
          ]
        }
      ],
      "multiplicity": 1
    },
    "mpi": {
      "bank_size": 1,
      "numerically_exact": false,
      "shared_memory_size": 10000
    },
    "mra": {
      "basis_order": 9,
      "basis_type": "interpolating",
      "boxes": [
        2,
        2,
        2
      ],
      "corner": [
        -1,
        -1,
        -1
      ],
      "max_scale": 20,
      "min_scale": -5
    },
    "printer": {
      "file_name": "45_pbe_.inp",
      "print_level": 0,
      "print_mpi": false,
      "print_prec": 6,
      "print_width": 75
    },
    "rsp_calculations": {},
    "scf_calculation": {
      "fock_operator": {
        "coulomb_operator": {
          "poisson_prec": 1e-06,
          "shared_memory": true
        },
        "exchange_operator": {
          "exchange_prec": -1.0,
          "poisson_prec": 1e-06
        },
        "kinetic_operator": {
          "derivative": "abgv_55"
        },
        "nuclear_operator": {
          "proj_prec": 1e-06,
          "shared_memory": true,
          "smooth_prec": 1e-06
        },
        "xc_operator": {
          "shared_memory": false,
          "xc_functional": {
            "cutoff": 0.0,
            "functionals": [
              {
                "coef": 1.0,
                "name": "pbe"
              }
            ],
            "spin": true
          }
        }
      },
      "initial_guess": {
        "file_basis": "initial_guess/mrchem.bas",
        "file_chk": "checkpoint/phi_scf",
        "file_gto_a": "initial_guess/mrchem.moa",
        "file_gto_b": "initial_guess/mrchem.mob",
        "file_gto_p": "initial_guess/mrchem.mop",
        "file_phi_a": "initial_guess/phi_a_scf",
        "file_phi_b": "initial_guess/phi_b_scf",
        "file_phi_p": "initial_guess/phi_p_scf",
        "localize": true,
        "method": "DFT (PBE)",
        "prec": 0.0001,
        "restricted": false,
        "type": "sad",
        "zeta": 2
      },
      "properties": {
        "dipole_moment": {
          "dip-1": {
            "operator": "h_e_dip",
            "precision": 1e-06,
            "r_O": [
              0.0,
              0.0,
              0.0
            ]
          }
        }
      },
      "scf_solver": {
        "checkpoint": false,
        "energy_thrs": 1e-06,
        "file_chk": "checkpoint/phi_scf",
        "final_prec": 1e-06,
        "helmholtz_prec": -1.0,
        "kain": 10,
        "localize": true,
        "max_iter": 200,
        "method": "DFT (PBE)",
        "orbital_thrs": 4.9999999999999996e-05,
        "rotation": 0,
        "start_prec": 1e-06
      }
    },
    "schema_name": "mrchem_input",
    "schema_version": 1
  },
  "output": {
    "properties": {
      "center_of_mass": [
        -4.850607038689896e-17,
        -1.3602417980643323e-18,
        6.314086402565466e-17
      ],
      "charge": 0,
      "dipole_moment": {
        "dip-1": {
          "magnitude": 0.7000889156819633,
          "r_O": [
            0.0,
            0.0,
            0.0
          ],
          "vector": [
            0.700088915611687,
            -1.6247413855523252e-06,
            9.785687714217418e-06
          ],
          "vector_el": [
            -1.9013538294595085,
            -1.6248752236040775e-06,
            9.785645004312116e-06
          ],
          "vector_nuc": [
            2.6014427450711954,
            1.338380517523774e-10,
            4.2709905302504645e-11
          ]
        }
      },
      "geometry": [
        {
          "symbol": "C",
          "xyz": [
            1.0454708660425407,
            0.0,
            0.0
          ]
        },
        {
          "symbol": "F",
          "xyz": [
            -0.44608985695745934,
            0.0,
            2.071517629
          ]
        },
        {
          "symbol": "F",
          "xyz": [
            -0.44608985695745934,
            0.0,
            -2.071517629
          ]
        },
        {
          "symbol": "H",
          "xyz": [
            2.1791174870425407,
            -1.706233595,
            0.0
          ]
        },
        {
          "symbol": "H",
          "xyz": [
            2.1791174870425407,
            1.706233595,
            0.0
          ]
        }
      ],
      "multiplicity": 1,
      "orbital_energies": {
        "energy": [
          -24.27142831105828,
          -24.27142592302623,
          -10.038682898666888,
          -1.1625507572542555,
          -1.1059433558478242,
          -0.6467459386533213,
          -0.49805790112468956,
          -0.49762386126292124,
          -0.49749910432108896,
          -0.370048204569936,
          -0.3671483918879831,
          -0.35272439685411955,
          -0.2992723675210854,
          -24.271428312797607,
          -24.27142592345313,
          -10.03868289918491,
          -1.1625507569458484,
          -1.105943356107618,
          -0.6467459507325168,
          -0.49805792450580344,
          -0.4976238601273614,
          -0.4974991151100094,
          -0.3700482033269432,
          -0.3671484046239659,
          -0.3527243968523353,
          -0.2992724097331952
        ],
        "occupation": [
          1.0,
          1.0,
          1.0,
          1.0,
          1.0,
          1.0,
          1.0,
          1.0,
          1.0,
          1.0,
          1.0,
          1.0,
          1.0,
          1.0,
          1.0,
          1.0,
          1.0,
          1.0,
          1.0,
          1.0,
          1.0,
          1.0,
          1.0,
          1.0,
          1.0,
          1.0
        ],
        "spin": [
          "a",
          "a",
          "a",
          "a",
          "a",
          "a",
          "a",
          "a",
          "a",
          "a",
          "a",
          "a",
          "a",
          "b",
          "b",
          "b",
          "b",
          "b",
          "b",
          "b",
          "b",
          "b",
          "b",
          "b",
          "b",
          "b"
        ],
        "sum_occupied": -128.75830292554983
      },
      "scf_energy": {
        "E_ee": 195.40906043654093,
        "E_eext": 0.0,
        "E_el": -316.4694984608369,
        "E_en": -723.287523167096,
        "E_kin": 238.25912435017221,
        "E_next": 0.0,
        "E_nn": 77.60031150510613,
        "E_nuc": 77.60031150510613,
        "E_tot": -238.86918695573078,
        "E_x": 0.0,
        "E_xc": -26.850160080454103
      }
    },
    "provenance": {
      "creator": "MRChem",
      "mpi_processes": 20,
      "nthreads": 6,
      "routine": "mrchem.x",
      "total_cores": 120,
      "version": "1.0.1"
    },
    "rsp_calculations": null,
    "scf_calculation": {
      "initial_energy": {
        "E_ee": 198.29253005019459,
        "E_eext": 0.0,
        "E_el": -315.7490436307343,
        "E_en": -736.9702553668783,
        "E_kin": 250.3809043422908,
        "E_next": 0.0,
        "E_nn": 77.60031150510613,
        "E_nuc": 77.60031150510613,
        "E_tot": -238.1487321256282,
        "E_x": 0.0,
        "E_xc": -27.45222265634145
      },
      "scf_solver": {
        "converged": true,
        "cycles": [
          {
            "energy_terms": {
              "E_ee": 194.82333188192587,
              "E_eext": 0.0,
              "E_el": -316.3894010003404,
              "E_en": -725.0470230276981,
              "E_kin": 240.66943164178753,
              "E_next": 0.0,
              "E_nn": 77.60031150510613,
              "E_nuc": 77.60031150510613,
              "E_tot": -238.78908949523426,
              "E_x": 0.0,
              "E_xc": -26.835141496355707
            },
            "energy_total": -238.78908949523426,
            "energy_update": 0.6403573696060789,
            "mo_residual": 0.40936327075727247,
            "wall_time": 138.493012713
          },
          {
            "energy_terms": {
              "E_ee": 196.40061968548412,
              "E_eext": 0.0,
              "E_el": -316.4501417522036,
              "E_en": -725.9357595805062,
              "E_kin": 240.06304228720688,
              "E_next": 0.0,
              "E_nn": 77.60031150510613,
              "E_nuc": 77.60031150510613,
              "E_tot": -238.84983024709746,
              "E_x": 0.0,
              "E_xc": -26.97804414438839
            },
            "energy_total": -238.84983024709746,
            "energy_update": 0.060740751863193054,
            "mo_residual": 0.1716528363456691,
            "wall_time": 107.012444309
          },
          {
            "energy_terms": {
              "E_ee": 194.99022789675547,
              "E_eext": 0.0,
              "E_el": -316.45949500546,
              "E_en": -722.9842008090886,
              "E_kin": 238.33783010120493,
              "E_next": 0.0,
              "E_nn": 77.60031150510613,
              "E_nuc": 77.60031150510613,
              "E_tot": -238.85918350035385,
              "E_x": 0.0,
              "E_xc": -26.80335219433177
            },
            "energy_total": -238.85918350035385,
            "energy_update": 0.00935325325639269,
            "mo_residual": 0.1256026834612727,
            "wall_time": 95.866387797
          },
          {
            "energy_terms": {
              "E_ee": 195.50266637907418,
              "E_eext": 0.0,
              "E_el": -316.4679245419993,
              "E_en": -723.6820312079083,
              "E_kin": 238.57231087175592,
              "E_next": 0.0,
              "E_nn": 77.60031150510613,
              "E_nuc": 77.60031150510613,
              "E_tot": -238.86761303689318,
              "E_x": 0.0,
              "E_xc": -26.860870584921123
            },
            "energy_total": -238.86761303689318,
            "energy_update": 0.008429536539324545,
            "mo_residual": 0.06335781429561894,
            "wall_time": 91.386541941
          },
          {
            "energy_terms": {
              "E_ee": 195.48168308692357,
              "E_eext": 0.0,
              "E_el": -316.46901977984,
              "E_en": -723.4253721602743,
              "E_kin": 238.33111472397317,
              "E_next": 0.0,
              "E_nn": 77.60031150510613,
              "E_nuc": 77.60031150510613,
              "E_tot": -238.86870827473385,
              "E_x": 0.0,
              "E_xc": -26.856445430462475
            },
            "energy_total": -238.86870827473385,
            "energy_update": 0.0010952378406727803,
            "mo_residual": 0.02112557564372699,
            "wall_time": 92.25432401
          },
          {
            "energy_terms": {
              "E_ee": 195.41220436519959,
              "E_eext": 0.0,
              "E_el": -316.4693110109721,
              "E_en": -723.2488615090433,
              "E_kin": 238.2157360089883,
              "E_next": 0.0,
              "E_nn": 77.60031150510613,
              "E_nuc": 77.60031150510613,
              "E_tot": -238.86899950586596,
              "E_x": 0.0,
              "E_xc": -26.848389876116677
            },
            "energy_total": -238.86899950586596,
            "energy_update": 0.00029123113210971496,
            "mo_residual": 0.011000450205205205,
            "wall_time": 89.516362828
          },
          {
            "energy_terms": {
              "E_ee": 195.39855212902197,
              "E_eext": 0.0,
              "E_el": -316.46939922060164,
              "E_en": -723.2480630348005,
              "E_kin": 238.2281702602395,
              "E_next": 0.0,
              "E_nn": 77.60031150510613,
              "E_nuc": 77.60031150510613,
              "E_tot": -238.8690877154955,
              "E_x": 0.0,
              "E_xc": -26.8480585750626
            },
            "energy_total": -238.8690877154955,
            "energy_update": 8.820962955269351e-05,
            "mo_residual": 0.005766972645528696,
            "wall_time": 89.069785328
          },
          {
            "energy_terms": {
              "E_ee": 195.40605942403013,
              "E_eext": 0.0,
              "E_el": -316.4694584330775,
              "E_en": -723.2829911032957,
              "E_kin": 238.25748356373424,
              "E_next": 0.0,
              "E_nn": 77.60031150510613,
              "E_nuc": 77.60031150510613,
              "E_tot": -238.86914692797134,
              "E_x": 0.0,
              "E_xc": -26.850010317546158
            },
            "energy_total": -238.86914692797134,
            "energy_update": 5.9212475832737255e-05,
            "mo_residual": 0.005475107474922019,
            "wall_time": 100.191730077
          },
          {
            "energy_terms": {
              "E_ee": 195.41011037122928,
              "E_eext": 0.0,
              "E_el": -316.4694843060103,
              "E_en": -723.2970687846113,
              "E_kin": 238.2682099902989,
              "E_next": 0.0,
              "E_nn": 77.60031150510613,
              "E_nuc": 77.60031150510613,
              "E_tot": -238.86917280090418,
              "E_x": 0.0,
              "E_xc": -26.85073588292728
            },
            "energy_total": -238.86917280090418,
            "energy_update": 2.5872932837955886e-05,
            "mo_residual": 0.004155889375476962,
            "wall_time": 105.826848281
          },
          {
            "energy_terms": {
              "E_ee": 195.40812350142136,
              "E_eext": 0.0,
              "E_el": -316.4694943200418,
              "E_en": -723.2927349446766,
              "E_kin": 238.26549197837693,
              "E_next": 0.0,
              "E_nn": 77.60031150510613,
              "E_nuc": 77.60031150510613,
              "E_tot": -238.86918281493567,
              "E_x": 0.0,
              "E_xc": -26.850374855163512
            },
            "energy_total": -238.86918281493567,
            "energy_update": 1.0014031488481123e-05,
            "mo_residual": 0.0026902543123655358,
            "wall_time": 100.140907266
          },
          {
            "energy_terms": {
              "E_ee": 195.40750779270945,
              "E_eext": 0.0,
              "E_el": -316.46949649007803,
              "E_en": -723.2884386123017,
              "E_kin": 238.26156369088895,
              "E_next": 0.0,
              "E_nn": 77.60031150510613,
              "E_nuc": 77.60031150510613,
              "E_tot": -238.8691849849719,
              "E_x": 0.0,
              "E_xc": -26.850129361374734
            },
            "energy_total": -238.8691849849719,
            "energy_update": 2.17003622537959e-06,
            "mo_residual": 0.0009838246582081164,
            "wall_time": 91.132530726
          },
          {
            "energy_terms": {
              "E_ee": 195.40833390717867,
              "E_eext": 0.0,
              "E_el": -316.4694977759595,
              "E_en": -723.2859641828586,
              "E_kin": 238.25819400865774,
              "E_next": 0.0,
              "E_nn": 77.60031150510613,
              "E_nuc": 77.60031150510613,
              "E_tot": -238.86918627085336,
              "E_x": 0.0,
              "E_xc": -26.850061508937262
            },
            "energy_total": -238.86918627085336,
            "energy_update": 1.2858814670835272e-06,
            "mo_residual": 0.0008839457734750638,
            "wall_time": 92.209782243
          },
          {
            "energy_terms": {
              "E_ee": 195.40896659353115,
              "E_eext": 0.0,
              "E_el": -316.4694981803895,
              "E_en": -723.2860082100519,
              "E_kin": 238.2576519736018,
              "E_next": 0.0,
              "E_nn": 77.60031150510613,
              "E_nuc": 77.60031150510613,
              "E_tot": -238.86918667528337,
              "E_x": 0.0,
              "E_xc": -26.85010853747051
            },
            "energy_total": -238.86918667528337,
            "energy_update": 4.0443001125822775e-07,
            "mo_residual": 0.000488007115587297,
            "wall_time": 92.698419392
          },
          {
            "energy_terms": {
              "E_ee": 195.4090630238868,
              "E_eext": 0.0,
              "E_el": -316.4694983500705,
              "E_en": -723.2865779073009,
              "E_kin": 238.25814196855822,
              "E_next": 0.0,
              "E_nn": 77.60031150510613,
              "E_nuc": 77.60031150510613,
              "E_tot": -238.8691868449644,
              "E_x": 0.0,
              "E_xc": -26.85012543521471
            },
            "energy_total": -238.8691868449644,
            "energy_update": 1.6968101590464357e-07,
            "mo_residual": 0.00032458846705347294,
            "wall_time": 96.382359498
          },
          {
            "energy_terms": {
              "E_ee": 195.40866831049692,
              "E_eext": 0.0,
              "E_el": -316.46949841981376,
              "E_en": -723.286212314277,
              "E_kin": 238.2581333280359,
              "E_next": 0.0,
              "E_nn": 77.60031150510613,
              "E_nuc": 77.60031150510613,
              "E_tot": -238.86918691470763,
              "E_x": 0.0,
              "E_xc": -26.85008774406958
            },
            "energy_total": -238.86918691470763,
            "energy_update": 6.974323696340434e-08,
            "mo_residual": 0.00019762803620368058,
            "wall_time": 100.639077795
          },
          {
            "energy_terms": {
              "E_ee": 195.40906043654093,
              "E_eext": 0.0,
              "E_el": -316.4694984608369,
              "E_en": -723.287523167096,
              "E_kin": 238.25912435017221,
              "E_next": 0.0,
              "E_nn": 77.60031150510613,
              "E_nuc": 77.60031150510613,
              "E_tot": -238.86918695573078,
              "E_x": 0.0,
              "E_xc": -26.850160080454103
            },
            "energy_total": -238.86918695573078,
            "energy_update": 4.1023156427399954e-08,
            "mo_residual": 0.00014703208795424034,
            "wall_time": 113.682006111
          }
        ],
        "wall_time": 1596.529651851
      },
      "success": true
    },
    "schema_name": "mrchem_output",
    "schema_version": 1,
    "success": true
  }
}
